Metadata-Version: 2.4
Name: agentcorrect
Version: 0.1.0
Summary: CI/CD guardrails for AI agents - prevent payment duplicates and data destruction
Home-page: https://github.com/yourusername/agentcorrect
Author: AgentCorrect Team
Author-email: AgentCorrect Team <support@agentcorrect.com>
License: MIT
Project-URL: Homepage, https://agentcorrect.com
Project-URL: Documentation, https://github.com/ishaan1345/agentcorrect#readme
Project-URL: Repository, https://github.com/ishaan1345/agentcorrect
Project-URL: Issues, https://github.com/ishaan1345/agentcorrect/issues
Keywords: ai,agent,safety,cicd,testing,payment,sql,security
Classifier: Development Status :: 5 - Production/Stable
Classifier: Intended Audience :: Developers
Classifier: Topic :: Software Development :: Quality Assurance
Classifier: Topic :: Software Development :: Testing
Classifier: License :: OSI Approved :: MIT License
Classifier: Programming Language :: Python :: 3
Classifier: Programming Language :: Python :: 3.8
Classifier: Programming Language :: Python :: 3.9
Classifier: Programming Language :: Python :: 3.10
Classifier: Programming Language :: Python :: 3.11
Classifier: Programming Language :: Python :: 3.12
Classifier: Operating System :: OS Independent
Requires-Python: >=3.8
License-File: LICENSE
Requires-Dist: sqlparse>=0.4.0
Requires-Dist: tldextract>=3.0.0
Provides-Extra: dev
Requires-Dist: pytest>=7.0.0; extra == "dev"
Requires-Dist: black>=22.0.0; extra == "dev"
Requires-Dist: mypy>=0.950; extra == "dev"
Requires-Dist: build>=0.7.0; extra == "dev"
Requires-Dist: twine>=4.0.0; extra == "dev"
Dynamic: author
Dynamic: home-page
Dynamic: license-file
Dynamic: requires-python
